xpython_utils/__init__.py
xpython_utils/log_utils.py
xpython_utils-1.0.dist-info/LICENSE
xpython_utils-1.0.dist-info/METADATA
xpython_utils-1.0.dist-info/WHEEL
xpython_utils-1.0.dist-info/top_level.txt
xpython_utils-1.0.dist-info/RECORD
